sanic_metrics/__init__.py
sanic_metrics/plugin.py
sanic_metrics/util.py
sanic_metrics/version.py
sanic_metrics-0.0.8.dist-info/entry_points.txt
sanic_metrics-0.0.8.dist-info/LICENSE.txt
sanic_metrics-0.0.8.dist-info/WHEEL
sanic_metrics-0.0.8.dist-info/METADATA
sanic_metrics-0.0.8.dist-info/RECORD
