Metadata-Version: 2.1
Name: sanic-metrics
Version: 0.0.8
Summary: Sanic plugin for capturing and logging access
Home-page: https://github.com/ashleysommer/sanic-metrics
License: Apache-2.0
Author: Ashley Sommer
Author-email: ashleysommer@gmail.com
Requires-Python: >=3.7,<4.0
Classifier: License :: OSI Approved :: Apache Software License
Classifier: Programming Language :: Python :: 3
Classifier: Programming Language :: Python :: 3.10
Classifier: Programming Language :: Python :: 3.7
Classifier: Programming Language :: Python :: 3.8
Classifier: Programming Language :: Python :: 3.9
Requires-Dist: aiofiles (>=0.4.0,<0.7.0)
Requires-Dist: python-dotenv (>=0.10.0,<0.11.0)
Requires-Dist: sanic (>=21.3.1,<22)
Requires-Dist: sanic-plugin-toolkit (>=1.2.0)
